{
    "CONVEYOR": [
        [
            "south",
            "empty",
            "empty",
            "empty",
            "empty"
        ],
        [
            "south",
            "empty",
            "empty",
            "empty",
            "empty"
        ],
        [
            "south",
            "empty",
            "empty",
            "empty",
            "empty"
        ],
        [
            "south",
            "empty",
            "empty",
            "empty",
            "empty"
        ],
        [
            "east",
            "empty",
            "north",
            "east",
            "east"
        ]
    ],
    "ROUTE": [
        [
            "1",
            "8",
            "0",
            "0",
            "0"
        ],
        [
            "5",
            "12",
            "0",
            "0",
            "0"
        ],
        [
            "8",
            "12",
            "0",
            "0",
            "0"
        ],
        [
            "10",
            "0",
            "15",
            "1",
            "1"
        ],
        [
            "11",
            "12",
            "14",
            "7",
            "15"
        ]
    ],
    "INSERTER": [
        [
            "empty",
            "east",
            "empty",
            "empty",
            "empty"
        ],
        [
            "empty",
            "east",
            "empty",
            "empty",
            "empty"
        ],
        [
            "empty",
            "east",
            "empty",
            "empty",
            "empty"
        ],
        [
            "empty",
            "empty",
            "north",
            "south",
            "south"
        ],
        [
            "empty",
            "east",
            "empty",
            "empty",
            "empty"
        ]
    ],
    "ASSEMBLER": [
        [
            "none",
            "none",
            "wooden-chest"
        ],
        [
            "none",
            "none",
            "none"
        ],
        [
            "none",
            "none",
            "none"
        ]
    ],
    "ASSEMBLER_COLLISION": [
        [
            "none",
            "none",
            "wooden-chest",
            "wooden-chest",
            "wooden-chest"
        ],
        [
            "none",
            "none",
            "wooden-chest",
            "wooden-chest",
            "wooden-chest"
        ],
        [
            "none",
            "none",
            "wooden-chest",
            "wooden-chest",
            "wooden-chest"
        ],
        [
            "none",
            "none",
            "none",
            "none",
            "none"
        ],
        [
            "none",
            "none",
            "none",
            "none",
            "none"
        ]
    ],
    "ITEM_FLOW": [
        [
            "wood",
            "wood",
            "none",
            "none",
            "none"
        ],
        [
            "wood",
            "wood",
            "none",
            "none",
            "none"
        ],
        [
            "wood",
            "wood",
            "none",
            "none",
            "none"
        ],
        [
            "wood",
            "none",
            "wood",
            "wooden-chest",
            "wooden-chest"
        ],
        [
            "wood",
            "wood",
            "wood",
            "wooden-chest",
            "wooden-chest"
        ]
    ],
    "INPUT_FLOW_RATE": [
        [
            "4805/24",
            "50",
            "0",
            "0",
            "0"
        ],
        [
            "3605/24",
            "50",
            "0",
            "0",
            "0"
        ],
        [
            "2405/24",
            "50",
            "0",
            "0",
            "0"
        ],
        [
            "1205/24",
            "0",
            "50",
            "50",
            "50"
        ],
        [
            "1205/24",
            "50",
            "50",
            "50",
            "100"
        ]
    ],
    "OUTPUT_FLOW_RATE": [
        [
            "3605/24",
            "50",
            "0",
            "0",
            "0"
        ],
        [
            "2405/24",
            "50",
            "0",
            "0",
            "0"
        ],
        [
            "1205/24",
            "50",
            "0",
            "0",
            "0"
        ],
        [
            "1205/24",
            "0",
            "50",
            "50",
            "50"
        ],
        [
            "5/24",
            "50",
            "0",
            "50",
            "100"
        ]
    ],
    "status": "SAT",
    "solving_time": 23.30005431175232
}